boilercore/__init__.py
boilercore/fits.py
boilercore/hashes.py
boilercore/modelfun.py
boilercore/paths.py
boilercore/syms.py
boilercore/testing.py
boilercore/types.py
boilercore/models/__init__.py
boilercore/models/fit.py
boilercore/models/geometry.py
boilercore/models/params.py
boilercore/models/paths.py
boilercore/models/trials.py
boilercore/models/types.py
boilercore/notebooks/__init__.py
boilercore/notebooks/namespaces.py
boilercore/notebooks/report.py
boilercore/notebooks/types.py
boilercore/stages/modelfun.ipynb
boilercore-2024.1.3.dist-info/LICENSE
boilercore-2024.1.3.dist-info/WHEEL
boilercore-2024.1.3.dist-info/METADATA
boilercore-2024.1.3.dist-info/RECORD
